{
  "properties": [
    {
      "name": "spring.security.oauth2.registration.client-id",
      "type": "java.lang.String",
      "description": "Description for spring.security.oauth2.registration.client-id."
    },
    {
      "name": "spring.security.oauth2.registration.client-secret",
      "type": "java.lang.String",
      "description": "Description for spring.security.oauth2.registration.client-secret."
    },
    {
      "name": "cloudinary.name",
      "type": "java.lang.String",
      "description": "Description for cloudinary.name."
    },
    {
      "name": "cloudinary.key",
      "type": "java.lang.String",
      "description": "Description for cloudinary.key."
    },
    {
      "name": "cloudinary.secret",
      "type": "java.lang.String",
      "description": "Description for cloudinary.secret."
      "name": "integration.itbook.base-url",
      "type": "java.lang.String",
      "description": "Description for integration.itbook.base-url."
    },
    {
      "name": "user-id-cron-job",
      "type": "java.lang.String",
      "description": "Description for user-id-cron-job."
    }
  ] }